{
  "Estimated Tea Production-Western": {
    "sub3": "Estimated Tea Production-Western",
    "unit": "Kg",
    "scale": "Million",
    "Sector": "Real Sector",
    "Source": "Sri Lanka Tea Board",
    "GeoArea": "Provincial",
    "Note": "",
    "Data last updated": "2022-01-18",
    "Update frequency": "End of August"
  },
  "Estimated Tea Production-Central": {
    "sub3": "Estimated Tea Production-Central",
    "unit": "Kg",
    "scale": "Million",
    "Sector": "Real Sector",
    "Source": "Sri Lanka Tea Board",
    "GeoArea": "Provincial",
    "Note": "",
    "Data last updated": "2022-01-18",
    "Update frequency": "End of August"
  },
  "Estimated Tea Production-Southern": {
    "sub3": "Estimated Tea Production-Southern",
    "unit": "Kg",
    "scale": "Million",
    "Sector": "Real Sector",
    "Source": "Sri Lanka Tea Board",
    "GeoArea": "Provincial",
    "Note": "",
    "Data last updated": "2022-01-18",
    "Update frequency": "End of August"
  },
  "Estimated Tea Production-Northern": {
    "sub3": "Estimated Tea Production-Northern",
    "unit": "Kg",
    "scale": "Million",
    "Sector": "Real Sector",
    "Source": "Sri Lanka Tea Board",
    "GeoArea": "Provincial",
    "Note": "",
    "Data last updated": "2022-01-18",
    "Update frequency": "End of August"
  },
  "Estimated Tea Production-Eastern": {
    "sub3": "Estimated Tea Production-Eastern",
    "unit": "Kg",
    "scale": "Million",
    "Sector": "Real Sector",
    "Source": "Sri Lanka Tea Board",
    "GeoArea": "Provincial",
    "Note": "",
    "Data last updated": "2022-01-18",
    "Update frequency": "End of August"
  },
  "Estimated Tea Production-North Western": {
    "sub3": "Estimated Tea Production-North Western",
    "unit": "Kg",
    "scale": "Million",
    "Sector": "Real Sector",
    "Source": "Sri Lanka Tea Board",
    "GeoArea": "Provincial",
    "Note": "",
    "Data last updated": "2022-01-18",
    "Update frequency": "End of August"
  },
  "Estimated Tea Production-North Central": {
    "sub3": "Estimated Tea Production-North Central",
    "unit": "Kg",
    "scale": "Million",
    "Sector": "Real Sector",
    "Source": "Sri Lanka Tea Board",
    "GeoArea": "Provincial",
    "Note": "",
    "Data last updated": "2022-01-18",
    "Update frequency": "End of August"
  },
  "Estimated Tea Production-Uva": {
    "sub3": "Estimated Tea Production-Uva",
    "unit": "Kg",
    "scale": "Million",
    "Sector": "Real Sector",
    "Source": "Sri Lanka Tea Board",
    "GeoArea": "Provincial",
    "Note": "",
    "Data last updated": "2022-01-18",
    "Update frequency": "End of August"
  },
  "Estimated Tea Production-Sabaragamuwa": {
    "sub3": "Estimated Tea Production-Sabaragamuwa",
    "unit": "Kg",
    "scale": "Million",
    "Sector": "Real Sector",
    "Source": "Sri Lanka Tea Board",
    "GeoArea": "Provincial",
    "Note": "",
    "Data last updated": "2022-01-18",
    "Update frequency": "End of August"
  },
  "No. of Tea Factories-Western": {
    "sub3": "No. of Tea Factories-Western",
    "unit": "Number",
    "scale": "",
    "Sector": "Real Sector",
    "Source": "Sri Lanka Tea Board",
    "GeoArea": "Provincial",
    "Note": "No. of Tea Factories (in operation)",
    "Data last updated": "2022-01-18",
    "Update frequency": "End of August"
  },
  "No. of Tea Factories-Central": {
    "sub3": "No. of Tea Factories-Central",
    "unit": "Number",
    "scale": "",
    "Sector": "Real Sector",
    "Source": "Sri Lanka Tea Board",
    "GeoArea": "Provincial",
    "Note": "No. of Tea Factories (in operation)",
    "Data last updated": "2022-01-18",
    "Update frequency": "End of August"
  },
  "No. of Tea Factories-Southern": {
    "sub3": "No. of Tea Factories-Southern",
    "unit": "Number",
    "scale": "",
    "Sector": "Real Sector",
    "Source": "Sri Lanka Tea Board",
    "GeoArea": "Provincial",
    "Note": "No. of Tea Factories (in operation)",
    "Data last updated": "2022-01-18",
    "Update frequency": "End of August"
  },
  "No. of Tea Factories-Northern": {
    "sub3": "No. of Tea Factories-Northern",
    "unit": "Number",
    "scale": "",
    "Sector": "Real Sector",
    "Source": "Sri Lanka Tea Board",
    "GeoArea": "Provincial",
    "Note": "No. of Tea Factories (in operation)",
    "Data last updated": "2022-01-18",
    "Update frequency": "End of August"
  },
  "No. of Tea Factories-Eastern": {
    "sub3": "No. of Tea Factories-Eastern",
    "unit": "Number",
    "scale": "",
    "Sector": "Real Sector",
    "Source": "Sri Lanka Tea Board",
    "GeoArea": "Provincial",
    "Note": "No. of Tea Factories (in operation)",
    "Data last updated": "2022-01-18",
    "Update frequency": "End of August"
  },
  "No. of Tea Factories-North Western": {
    "sub3": "No. of Tea Factories-North Western",
    "unit": "Number",
    "scale": "",
    "Sector": "Real Sector",
    "Source": "Sri Lanka Tea Board",
    "GeoArea": "Provincial",
    "Note": "No. of Tea Factories (in operation)",
    "Data last updated": "2022-01-18",
    "Update frequency": "End of August"
  },
  "No. of Tea Factories-North Central": {
    "sub3": "No. of Tea Factories-North Central",
    "unit": "Number",
    "scale": "",
    "Sector": "Real Sector",
    "Source": "Sri Lanka Tea Board",
    "GeoArea": "Provincial",
    "Note": "No. of Tea Factories (in operation)",
    "Data last updated": "2022-01-18",
    "Update frequency": "End of August"
  },
  "No. of Tea Factories-Uva": {
    "sub3": "No. of Tea Factories-Uva",
    "unit": "Number",
    "scale": "",
    "Sector": "Real Sector",
    "Source": "Sri Lanka Tea Board",
    "GeoArea": "Provincial",
    "Note": "No. of Tea Factories (in operation)",
    "Data last updated": "2022-01-18",
    "Update frequency": "End of August"
  },
  "No. of Tea Factories-Sabaragamuwa": {
    "sub3": "No. of Tea Factories-Sabaragamuwa",
    "unit": "Number",
    "scale": "",
    "Sector": "Real Sector",
    "Source": "Sri Lanka Tea Board",
    "GeoArea": "Provincial",
    "Note": "No. of Tea Factories (in operation)",
    "Data last updated": "2022-01-18",
    "Update frequency": "End of August"
  },
  "No. of Tea Factories": {
    "sub3": "No. of Tea Factories",
    "unit": "Number",
    "scale": "",
    "Sector": "Real Sector",
    "Source": "Sri Lanka Tea Board",
    "GeoArea": "National",
    "Note": "No. of Tea Factories (in operation)",
    "Data last updated": "2022-01-18",
    "Update frequency": "End of August"
  },
  "Estimated Rubber Production-Western": {
    "sub3": "Estimated Rubber Production-Western",
    "unit": "Kg",
    "scale": "Million",
    "Sector": "Real Sector",
    "Source": "Rubber Development Department",
    "GeoArea": "Provincial",
    "Note": "",
    "Data last updated": "2022-01-18",
    "Update frequency": "End of August"
  },
  "Estimated Rubber Production-Central": {
    "sub3": "Estimated Rubber Production-Central",
    "unit": "Kg",
    "scale": "Million",
    "Sector": "Real Sector",
    "Source": "Rubber Development Department",
    "GeoArea": "Provincial",
    "Note": "",
    "Data last updated": "2022-01-18",
    "Update frequency": "End of August"
  },
  "Estimated Rubber Production-Southern": {
    "sub3": "Estimated Rubber Production-Southern",
    "unit": "Kg",
    "scale": "Million",
    "Sector": "Real Sector",
    "Source": "Rubber Development Department",
    "GeoArea": "Provincial",
    "Note": "",
    "Data last updated": "2022-01-18",
    "Update frequency": "End of August"
  },
  "Estimated Rubber Production-Northern": {
    "sub3": "Estimated Rubber Production-Northern",
    "unit": "Kg",
    "scale": "Million",
    "Sector": "Real Sector",
    "Source": "Rubber Development Department",
    "GeoArea": "Provincial",
    "Note": "",
    "Data last updated": "2022-01-18",
    "Update frequency": "End of August"
  },
  "Estimated Rubber Production-Eastern": {
    "sub3": "Estimated Rubber Production-Eastern",
    "unit": "Kg",
    "scale": "Million",
    "Sector": "Real Sector",
    "Source": "Rubber Development Department",
    "GeoArea": "Provincial",
    "Note": "",
    "Data last updated": "2022-01-18",
    "Update frequency": "End of August"
  },
  "Estimated Rubber Production-North Western": {
    "sub3": "Estimated Rubber Production-North Western",
    "unit": "Kg",
    "scale": "Million",
    "Sector": "Real Sector",
    "Source": "Rubber Development Department",
    "GeoArea": "Provincial",
    "Note": "",
    "Data last updated": "2022-01-18",
    "Update frequency": "End of August"
  },
  "Estimated Rubber Production-North Central": {
    "sub3": "Estimated Rubber Production-North Central",
    "unit": "Kg",
    "scale": "Million",
    "Sector": "Real Sector",
    "Source": "Rubber Development Department",
    "GeoArea": "Provincial",
    "Note": "",
    "Data last updated": "2022-01-18",
    "Update frequency": "End of August"
  },
  "Estimated Rubber Production-Uva": {
    "sub3": "Estimated Rubber Production-Uva",
    "unit": "Kg",
    "scale": "Million",
    "Sector": "Real Sector",
    "Source": "Rubber Development Department",
    "GeoArea": "Provincial",
    "Note": "",
    "Data last updated": "2022-01-18",
    "Update frequency": "End of August"
  },
  "Estimated Rubber Production-Sabaragamuwa": {
    "sub3": "Estimated Rubber Production-Sabaragamuwa",
    "unit": "Kg",
    "scale": "Million",
    "Sector": "Real Sector",
    "Source": "Rubber Development Department",
    "GeoArea": "Provincial",
    "Note": "",
    "Data last updated": "2022-01-18",
    "Update frequency": "End of August"
  },
  "Estimated Coconut Production-Central": {
    "sub3": "Estimated Coconut Production-Central",
    "unit": "Nuts",
    "scale": "Million",
    "Sector": "Real Sector",
    "Source": "Coconut Research Institute",
    "GeoArea": "Provincial",
    "Note": "",
    "Data last updated": "2022-01-18",
    "Update frequency": "End of August"
  },
  "Estimated Coconut Production-Eastern": {
    "sub3": "Estimated Coconut Production-Eastern",
    "unit": "Nuts",
    "scale": "Million",
    "Sector": "Real Sector",
    "Source": "Coconut Research Institute",
    "GeoArea": "Provincial",
    "Note": "",
    "Data last updated": "2022-01-18",
    "Update frequency": "End of August"
  }
}